refet/__init__.py
refet/calcs.py
refet/daily.py
refet/hourly.py
refet/units.py
refet-0.4.0.dist-info/LICENSE.txt
refet-0.4.0.dist-info/METADATA
refet-0.4.0.dist-info/WHEEL
refet-0.4.0.dist-info/top_level.txt
refet-0.4.0.dist-info/RECORD
