Metadata-Version: 2.1
Name: refet
Version: 0.4.0
Summary: ASCE Standardized Reference Evapotranspiration Functions
Author-email: Charles Morton <charles.morton@dri.edu>
Project-URL: Homepage, https://github.com/WSWUP/RefET
Project-URL: Bug Tracker, https://github.com/WSWUP/RefET/issues
Classifier: Programming Language :: Python :: 3
Classifier: License :: OSI Approved :: Apache Software License
Classifier: Operating System :: OS Independent
Requires-Python: >=3.6
License-File: LICENSE.txt
Requires-Dist: numpy (>=1.10.0)
